{
    "General" : "Allgemein",
    "Graphics" : "Grafik",
    "Audio" : "Audio",
    "Controls" : "Steuerung",
    "Back" : "Zurück",
    "Settings" : "Einstellungen",
    "Language" : "Sprache",
    "GeneralVolume" : "Allgemein",
    "MusicVolume" : "Musik",
    "SFXVolume" : "Soundeffekte",
    "StartGame" : "Starten",
    "Credits" : "Credits",
    "QuitGame" : "Beenden",
    "Resolution" : "Auflösung",
    "Fullscreen" : "Vollbild",
    "MoveForward" : "Vorwärts bewegen",
    "MoveBackward" : "Rückwärts bewegen",
    "MoveLeft" : "Nach links bewegen",
    "MoveRight" : "Nach rechts bewegen",
    "Jump" : "Springen",
    "Crouch" : "Ducken",
    "Sprint" : "Sprinten",
    "Interact" : "Interagieren",
    "Reset" : "Zurücksetzen"
}